seqfkit/__init__.py
seqfkit/glimpse.py
seqfkit/utils.py
seqfkit-0.1.5.dist-info/LICENSE
seqfkit-0.1.5.dist-info/METADATA
seqfkit-0.1.5.dist-info/WHEEL
seqfkit-0.1.5.dist-info/entry_points.txt
seqfkit-0.1.5.dist-info/top_level.txt
seqfkit-0.1.5.dist-info/RECORD
