Metadata-Version: 2.1
Name: seqfkit
Version: 0.1.5
Summary: Some useful tools to handle sequences (DNA/RNA/Protein).
Author-email: Zhang Yujian <Chouuken@outlook.com>
License:                                  Apache License
Project-URL: Homepage, https://github.com/Chou-Uken/seqfkit
Classifier: Programming Language :: Python :: 3
Classifier: License :: OSI Approved :: Apache Software License
Classifier: Operating System :: OS Independent
Requires-Python: >=3.10
License-File: LICENSE
Requires-Dist: click
